{
  "version": "7",
  "dialect": "postgresql",
  "entries": [
    {
      "idx": 0,
      "version": "7",
      "when": 1778491617710,
      "tag": "0000_aspiring_mordo",
      "breakpoints": true
    },
    {
      "idx": 1,
      "version": "7",
      "when": 1778491655084,
      "tag": "0001_unusual_puff_adder",
      "breakpoints": true
    },
    {
      "idx": 2,
      "version": "7",
      "when": 1778528814633,
      "tag": "0002_round_forgotten_one",
      "breakpoints": true
    },
    {
      "idx": 3,
      "version": "7",
      "when": 1783496021583,
      "tag": "0003_mysterious_exiles",
      "breakpoints": true
    },
    {
      "idx": 4,
      "version": "7",
      "when": 1783500368006,
      "tag": "0004_typical_timeslip",
      "breakpoints": true
    }
  ]
}